setup.py
digPhoneExtractor/__init__.py
digPhoneExtractor/phone_extractor.py
digPhoneExtractor/test.py
digPhoneExtractor/twilio_api.py
digPhoneExtractor.egg-info/PKG-INFO
digPhoneExtractor.egg-info/SOURCES.txt
digPhoneExtractor.egg-info/dependency_links.txt
digPhoneExtractor.egg-info/requires.txt
digPhoneExtractor.egg-info/top_level.txt
digPhoneExtractor/pnmatcher/__init__.py
digPhoneExtractor/pnmatcher/pnmatcher.py
digPhoneExtractor/pnmatcher/core/__init__.py
digPhoneExtractor/pnmatcher/core/cleaner.py
digPhoneExtractor/pnmatcher/core/extractor.py
digPhoneExtractor/pnmatcher/core/normalizer.py
digPhoneExtractor/pnmatcher/core/preprocessor.py
digPhoneExtractor/pnmatcher/core/tokenizer.py
digPhoneExtractor/pnmatcher/core/validator.py
digPhoneExtractor/pnmatcher/core/common/__init__.py
digPhoneExtractor/pnmatcher/core/common/datetime_helper.py
digPhoneExtractor/pnmatcher/res/__init__.py
digPhoneExtractor/pnmatcher/res/area_code/__init__.py
test/__init__.py
test/test_phone_extractor.py
test/groundtruth/__init__.py