Metadata-Version: 1.1
Name: digPhoneExtractor
Version: 0.3.7
Summary: digPhoneExtractor
Home-page: https://github.com/ZwEin27/dig-phone-extractor
Author: Lingzhe Teng
Author-email: zwein27@gmail.com
License: UNKNOWN
Download-URL: https://github.com/ZwEin27/dig-phone-extractor
Keywords: phone_number,extractor
Platform: UNKNOWN
